interactive_cli/__init__.py
interactive_cli/async_cli_app.py
interactive_cli/blocking_cli_app.py
interactive_cli/cli_app.py
interactive_cli/cli_command.py
interactive_cli/cli_page.py
interactive_cli/cli_print_context.py
interactive_cli/static.py
interactive_cli/utils.py
interactive_cli/VERSION
interactive_cli/version.py
interactive_cli-0.1.0.dist-info/LICENSE
interactive_cli-0.1.0.dist-info/METADATA
interactive_cli-0.1.0.dist-info/WHEEL
interactive_cli-0.1.0.dist-info/RECORD
