Metadata-Version: 2.1
Name: interactive-cli
Version: 0.1.0
Summary: 
Author: miile7
Author-email: miile7@gmx.de
Requires-Python: >=3.8,<4.0
Classifier: Programming Language :: Python :: 3
Classifier: Programming Language :: Python :: 3.8
Classifier: Programming Language :: Python :: 3.9
Classifier: Programming Language :: Python :: 3.10
Classifier: Programming Language :: Python :: 3.11
Requires-Dist: tabulate (>=0.9.0,<0.10.0)
